statismo/__init__.py
statismo/admin.py
statismo/apps.py
statismo/metrics.py
statismo/models.py
statismo/tasks.py
statismo/collectors/__init__.py
statismo/collectors/base.py
statismo/collectors/db.py
statismo/collectors/redis.py
statismo/migrations/0001_initial.py
statismo/migrations/__init__.py
statismo-0.2.2.dist-info/METADATA
statismo-0.2.2.dist-info/WHEEL
statismo-0.2.2.dist-info/RECORD
