Metadata-Version: 2.4
Name: statismo
Version: 0.2.2
Summary: A minimal collector of custom metrics for django apps.
Project-URL: Repository, https://github.com/gotrellis/statismo
Requires-Python: >=3.10
Requires-Dist: boto3>=1.0.0
Requires-Dist: celery>=5.0.0
Requires-Dist: django>=4.0.0
Provides-Extra: dev
Requires-Dist: pytest-django>=4.5.0; extra == 'dev'
Requires-Dist: pytest-mock>=3.10.0; extra == 'dev'
Requires-Dist: pytest>=7.0.0; extra == 'dev'
Provides-Extra: redis
Requires-Dist: redis>=5.2.1; extra == 'redis'
